Workbook

Sheet Overview
A1: Work-Alpha
A2: Month 1: from zero to an application-ready research pack
A3: End goal | B3: By Sunday 27 September 2026 you hold a sendable PhD application pack: a chosen research question, 15 verified papers with structured notes, a gap matrix, one dataset explored with a figure and a table, a 15-name supervisor directory with deadlines, a 2-page proposal that survived a hostile review, and three outreach emails ready to send.
A5: Planned task minutes | B5: =SUM(Plan!H2:H43) -> 2100
A6: Done task minutes | B6: =SUMIF(Plan!I2:I43,"x",Plan!H2:H43) -> 0
A7: Progress | B7: =IF(B5=0,0,B6/B5) -> 0
A8: Tasks done | B8: =COUNTIF(Plan!I2:I43,"x")&" / "&COUNTA(Plan!E2:E43) -> 0 / 42
A9: Minutes on the clock | B9: =SUM(Plan!J2:J43) -> 0
A11: Goal | B11: Name | C11: Day | D11: Tasks done | E11: Tasks | F11: Progress | G11: The test
A12: G1 | B12: Decision made, tools ready | C12: 1 | D12: =COUNTIFS(Plan!D2:D43,A12,Plan!I2:I43,"x") -> 0 | E12: =COUNTIF(Plan!D2:D43,A12) -> 5 | F12: =IF(E12=0,0,D12/E12) -> 0 | G12: One track chosen with a written 3-line reason. Zotero, Drive tree, Colab and the prompt library all open in one click.
A13: G2 | B13: Literature map | C13: 2 | D13: =COUNTIFS(Plan!D2:D43,A13,Plan!I2:I43,"x") -> 0 | E13: =COUNTIF(Plan!D2:D43,A13) -> 5 | F13: =IF(E13=0,0,D13/E13) -> 0 | G13: 15 papers verified (DOI or PDF in hand), 8 venues recorded, reading order fixed.
A14: G3 | B14: Ten papers read, gap found | C14: 4 | D14: =COUNTIFS(Plan!D2:D43,A14,Plan!I2:I43,"x") -> 0 | E14: =COUNTIF(Plan!D2:D43,A14) -> 12 | F14: =IF(E14=0,0,D14/E14) -> 0 | G14: 10 structured notes complete, gap matrix filled, one sentence naming the gap.
A15: G4 | B15: Data touched | C15: 5 | D15: =COUNTIFS(Plan!D2:D43,A15,Plan!I2:I43,"x") -> 0 | E15: =COUNTIF(Plan!D2:D43,A15) -> 5 | F15: =IF(E15=0,0,D15/E15) -> 0 | G15: One dataset loaded in Colab, four sanity checks passed, one figure and one summary table saved.
A16: G5 | B16: People and dates | C16: 6 | D16: =COUNTIFS(Plan!D2:D43,A16,Plan!I2:I43,"x") -> 0 | E16: =COUNTIF(Plan!D2:D43,A16) -> 5 | F16: =IF(E16=0,0,D16/E16) -> 0 | G16: 15 supervisors ranked A/B/C, scholarship rounds dated, five loose ends assigned.
A17: G6 | B17: Proposal survives review | C17: 7 | D17: =COUNTIFS(Plan!D2:D43,A17,Plan!I2:I43,"x") -> 0 | E17: =COUNTIF(Plan!D2:D43,A17) -> 5 | F17: =IF(E17=0,0,D17/E17) -> 0 | G17: 2-page proposal v2 exists and the hostile reviewer's top three objections are answered in the text.
A18: G7 | B18: Pack ready to send | C18: 8 | D18: =COUNTIFS(Plan!D2:D43,A18,Plan!I2:I43,"x") -> 0 | E18: =COUNTIF(Plan!D2:D43,A18) -> 5 | F18: =IF(E18=0,0,D18/E18) -> 0 | G18: Proposal final, CV bullets updated, three emails drafted, month 2 plan written.
A20: Legend: type x in Plan!I (Done) when a task is finished; type minutes in Plan!J. Everything on this sheet recalculates. Dates, minutes and seed papers are Claude's plan (2026-09-04); scores you type are yours.

Sheet Plan
A1: Day | B1: Date | C1: Theme | D1: Goal | E1: Task id | F1: Task | G1: Kind | H1: Minutes | I1: Done (x) | J1: Minutes spent | K1: Why | L1: Steps | M1: AI prompt | N1: What you hand in | O1: Done means
A2: 1 | B2: 2026-09-05 | C2: Decide and set up | D2: G1 | E2: d1t1 | F2: Build the workspace in one sitting | G2: setup | H2: 45 | K2: Every later task assumes these five things exist. Doing them once, together, removes every 'where do I put this' moment for the rest of the month. | L2: 1. Google Drive: create folder Work-Alpha with subfolders 00-Admin, 01-Literature, 02-Targets, 03-Paper (with data, code, output, drafts inside), 04-Proposal, 05-Outreach 2. Install Zotero (zotero.org) and the browser connector. Create one collection called Month-1 3. Open Google Colab (colab.research.google.com), make a notebook called 2026-09-05_setup.ipynb, run print('ok'), save to 03-Paper/code 4. Make a Google Scholar profile alert: search your track's keywords, click Create alert 5. Bookmark folder 'Work-Alpha' in your browser with: this app, Drive, Zotero web, Colab, Scholar, Connected Papers, OpenAlex | M2: I am setting up a research workspace for a PhD application. Give me a one-line description to paste into a README for each of these Drive folders: 00-Admin, 01-Literature, 02-Targets, 03-Paper, 04-Proposal, 05-Outreach. Under 15 words each. | N2: Drive tree exists, Zotero installed, Colab notebook saved, one Scholar alert, one bookmark folder. | O2: You can open all five in under a minute from the bookmark folder.
A3: 1 | B3: 2026-09-05 | C3: Decide and set up | D3: G1 | E3: d1t2 | F3: Write both research questions in one page each | G3: think | H3: 60 | K3: You cannot choose between two vague ideas. Forcing each into the same one-page shape makes the comparison honest. | L3: 1. Open a Google Doc: 2026-09-05_two-questions_v1 2. For track A and track B, fill the same six headings: Question (one sentence), Why it matters (three lines), Data I can actually get (name the file), Method in one sentence, Who would supervise this (two names or 'unknown'), What I already know (courses, dissertation, code) 3. Use the AI prompt below to sharpen each question, then rewrite it in your own words 4. Save to 00-Admin | M3: Here is a draft PhD research question: [PASTE]. Rewrite it three ways: (1) narrower and testable with one dataset, (2) as a causal question naming the treatment and the outcome, (3) as a policy question a minister would care about. Then list the two most likely referee objections to each. Keep every line under 25 words. | N3: One Google Doc with two one-page question sheets. | O3: Every heading has real words under it for both tracks, including 'unknown' where that is the truth.
A4: 1 | B4: 2026-09-05 | C4: Decide and set up | D4: G1 | E4: d1t3 | F4: Score the tracks and decide | G4: think | H4: 45 | K4: A decision written with numbers is one you will stop re-opening every weekend. | L4: 1. In the Decision page of this app, score each track 1 to 5 on the six criteria (the app sums them) 2. Read the sums. If they are within 3 points, the tie-break is 'which dataset can I download tonight' 3. Set the active track in Settings (A, B, or Both with a primary) 4. Write the three-line reason in the Decision page; it is shown on the dashboard from now on | M4: I have to choose between two PhD directions. Track A: [PASTE A QUESTION]. Track B: [PASTE B QUESTION]. My background: [MSc in X, dissertation on Y, know Python at level Z]. Score each track 1 to 5 on: data access within a month, fit to my background, supervisor supply in [countries], scholarship fit, publishability in 2 years, my genuine interest. Give a one-sentence justification per score and a recommendation. Then tell me the single strongest reason to pick the other one. | N4: Decision recorded in the app with scores and a reason. | O4: The Settings page shows the chosen track and the dashboard shows the reason.
A5: 1 | B5: 2026-09-05 | C5: Decide and set up | D5: G1 | E5: d1t4 | F5: Load the prompt library and the note template | G5: setup | H5: 60 | K5: Reading with a fixed template is what turns 10 papers into a gap matrix. Deciding the template now means every note from Day 3 has the same shape. | L5: 1. Open the Prompts page of this app. Read the seven prompts once; you will reuse them all month 2. Copy the Paper Note template into a Google Doc named TEMPLATE_paper-note and put it in 01-Literature 3. Copy the Research Log template into 00-Admin 4. Test the Paper Note prompt on any PDF you already own to see the shape of the answer | M5: You are my reading assistant. When I paste a paper's abstract, introduction and conclusion, answer under exactly these headings and nothing else: Question, Data (source, years, N), Method (one sentence), Main result (with the number), Identification worry, What it leaves open, One sentence I could cite it for. Under 40 words per heading. Say 'not stated' rather than guessing. | N5: Two template Docs, and one test note. | O5: The test note has all seven headings filled from a real paper.
A6: 1 | B6: 2026-09-05 | C6: Decide and set up | D6: G1 | E6: d1t5 | F6: Record the loose ends and the calendar | G6: people | H6: 60 | K6: Five admin facts decide whether an application is even possible. Finding them out costs an hour now or a rejection later. | L6: 1. In the People page, Loose ends tab, fill: English test (which, valid until), partner visa rule for each target country, domestic tuition status, alumni library access (which library, proxy URL), scholarship round dates 2. For anything you cannot find in 10 minutes, write 'waiting: asked [who] on [date]' and move on 3. Put every known deadline in the Deadlines tab; the dashboard counts down to the nearest one 4. Email your former university library about alumni access today (template in Prompts) | M6: Write an email under 120 words to [University] library asking whether alumni have remote database access, which databases, and how to activate it. Polite, no adverbs, one question per sentence. | N6: Five loose-end rows and at least one dated deadline. | O6: No loose end row is blank; each says a fact or names who you asked.
A7: 2 | B7: 2026-09-06 | C7: Map the literature | D7: G2 | E7: d2t1 | F7: Verify the 15 seed papers into Zotero | G7: read | H7: 60 | K7: A citation exists only if the real paper is in the library. Fifteen verified papers is the whole floor of the proposal. | L7: 1. Open the Library page: the 15 seeds for your track are pre-filled 2. For each: search Google Scholar, click the Zotero connector to save it, tick Verified in the Library page when the PDF or DOI is in Zotero 3. If a paper cannot be found in 5 minutes, mark it Not found and replace it using the prompt below 4. Use Unpaywall (the browser extension) for open versions; use the alumni proxy if you got one; otherwise email the author with the request template | M7: I could not find this paper: [CITATION]. Suggest three substitutes published 2015 or later on the same question in a top field journal, with authors, year, journal and a one-line reason each. Do not invent papers: if unsure, say so. | N7: 15 rows in Library marked Verified, each with a DOI or PDF in Zotero. | O7: Zotero collection Month-1 shows 15 items with attachments or DOIs.
A8: 2 | B8: 2026-09-06 | C8: Map the literature | D8: G2 | E8: d2t2 | F8: Snowball forward and backward | G8: read | H8: 45 | K8: Seeds are what I know. Snowballing is how you find what the field knows that I do not. | L8: 1. Open connectedpapers.com, paste your three most central seeds one at a time 2. From each graph, save the two most-cited recent papers you had not seen into Zotero 3. In Scholar, click 'Cited by' on your oldest seed and sort by date; save one 2023 or later paper 4. Add every new find to the Library page as a row with Verified unticked | M8: Here are 15 papers on [TOPIC]: [PASTE LIST]. Which three are the hubs everything else cites? Which subtopic is missing from this list entirely? Name two papers that would fill it, and say if you are unsure they exist. | N8: 6 to 9 new candidate rows in Library. | O8: Library has at least 21 rows.
A9: 2 | B9: 2026-09-06 | C9: Map the literature | D9: G2 | E9: d2t3 | F9: Build the journal map | G9: read | H9: 45 | K9: Knowing where the conversation happens tells you where your paper belongs and which journals a supervisor publishes in. | L9: 1. The Venues tab lists 8 journals for your track; for each, open its website and note: open access yes/no, typical article length, latest issue date 2. Rank them 1 to 8 for where you would first submit 3. Tick 'read regularly' on three; set a Scholar alert for each | M9: For the journal [NAME], tell me: its scope in one line, whether it publishes empirical development or finance papers from South Asia, its rough acceptance difficulty (top field, strong field, solid), and one 2023 or later paper close to [MY QUESTION]. If you are unsure about any item, say unsure. | N9: 8 venue rows completed and ranked. | O9: Three venues carry a Scholar alert.
A10: 2 | B10: 2026-09-06 | C10: Map the literature | D10: G2 | E10: d2t4 | F10: Fix the reading order | G10: read | H10: 60 | K10: Read the review paper first and the frontier paper last, or you will spend Day 3 confused. | L10: 1. Sort the Library so that reviews and surveys come first, the two most-cited empirical papers next, then the rest by year descending 2. Number the first ten in the Order column; those are Days 3 and 4 3. Download all ten PDFs into 01-Literature with the naming rule 4. Read the abstract of each of the ten once, five minutes each, and write one line in Notes: 'this is about X' | M10: Order these papers for a newcomer to read in two days, five per day: [LIST]. Reviews first, then the two most-cited empirical papers, then the most recent frontier. Give the order and one line per paper on what to look for while reading it. | N10: Order column filled 1 to 10, ten PDFs downloaded. | O10: Ten PDFs are in 01-Literature with correct names.
A11: 2 | B11: 2026-09-06 | C11: Map the literature | D11: G2 | E11: d2t5 | F11: Write the one-page literature sketch | G11: write | H11: 60 | K11: Writing a paragraph before reading closely gives you a hypothesis about the field that Days 3 and 4 will confirm or break. | L11: 1. New Doc 2026-09-06_lit-sketch_v1 in 01-Literature 2. Four paragraphs: what the field asks; what methods it uses; what it finds; what nobody seems to answer 3. Use the prompt below with your ten abstracts; then rewrite every sentence yourself, no pasted sentences 4. Cite papers as (Author, Year) only; the bibliography comes from Zotero later | M11: Here are ten abstracts: [PASTE]. Write a 250-word sketch of the field with four paragraphs: the questions, the methods, the findings, the gaps. Use (Author Year) citations only from these abstracts. Flag any claim you are unsure the abstracts support. | N11: One page, four paragraphs, saved. | O11: The Gaps paragraph names one concrete missing thing.
A12: 3 | B12: 2026-09-12 | C12: Read five papers properly | D12: G3 | E12: d3t1 | F12: Paper 1 (the review): full structured note | G12: read | H12: 50 | K12: The review is your map. Its note will be twice as long as the others and that is right. | L12: 1. Open the PDF, read introduction and conclusion first, then skim the body headings 2. Paste abstract, intro and conclusion into the Paper Note prompt (from Prompts page) 3. Read the AI answer against the paper: fix every line the paper does not support 4. Save as a Note in the Library row (Notes column opens an editor) and as a Doc in 01-Literature | M12: USE: Paper Note prompt (Prompts page). | N12: One complete structured note. | O12: All seven headings filled, none says 'not stated' unless the paper truly does not state it.
A13: 3 | B13: 2026-09-12 | C13: Read five papers properly | D13: G3 | E13: d3t2 | F13: Paper 2: full structured note | G13: read | H13: 50 | K13: Same shape, same discipline. The value is in the sameness. | L13: 1. Same four steps as Paper 1 2. Add one extra line at the end: 'differs from Paper 1 by...' | M13: USE: Paper Note prompt. | N13: One structured note. | O13: Seven headings plus the 'differs from' line.
... A43: 8 | B43: 2026-09-27 | C43: Finish the pack | D43: G7 | E43: d8t5 | F43: Month review and the month 2 plan | G43: review | H43: 45 | K43: The last hour of a month is worth more than the first. | L43: 1. Fill the Month review page: hours logged vs planned, goals met vs missed, the three biggest lessons 2. Month 2 goal options: (a) replicate one table from your central paper on your data, (b) apply to the first round, (c) a second dataset. Pick one 3. Write the month 2 goal sentence and the first two days' tasks 4. Export the whole app state as JSON to 00-Admin (Settings page, Export) | M43: Here is my month 1 review: [PASTE]. Propose a month 2 plan with the same shape (two days a week, five hours a day, four weekends) that turns the proposal into a first empirical result. Name the end goal in one sentence and the goal for each weekend. | N43: Month review page filled, month 2 goal saved, JSON exported. | O43: The dashboard shows the month 2 goal sentence and a JSON file is in 00-Admin.

Sheet Prompts
A1: Name | B1: When | C1: Prompt text
A2: Paper Note | B2: Every paper you read closely (Days 3 and 4) | C2: You are my reading assistant. Here are the abstract, introduction and conclusion of a paper. Answer under exactly these headings and nothing else: Question; Data (source, years, N); Method (one sentence); Main result (with the number); Identification worry; What it leaves open; One sentence I could cite it for. Under 40 words per heading. Write 'not stated' rather than guessing. Do not add headings. [PASTE TEXT]
A3: Hostile reviewer | B3: Any gap sentence or proposal draft. Always in a fresh chat with nothing else pasted. | C3: You are a sceptical referee for a top field journal in economics. You have not seen anything about this project before. Read the text below and give: the three objections most likely to lead to rejection, ranked; for each, the specific sentence or paragraph it targets and what evidence would remove it; one thing the author claims that the text does not support; and one strength, in one line. Be blunt, be specific, do not soften. [PASTE TEXT]
A4: Section drafter | B4: Drafting one proposal section from its outline sentence (Day 7) | C4: Draft the [SECTION NAME] section of a two-page PhD research proposal in economics. It must carry this sentence: [SENTENCE]. Use only these sources, cited as (Author Year): [LIST]. 100 to 160 words, formal, no adverbs, no rhetorical questions, no 'in today's world'. If a claim needs a citation I have not given, write [CITATION NEEDED] rather than inventing one.
A5: Outreach email | B5: Positioning paragraphs and emails (Days 6 and 8) | C5: Write an email to Professor [SURNAME] from a prospective PhD student. Rules: under 200 words; the first sentence must refer to a specific finding in their [YEAR] paper [TITLE]; the second states my question in one sentence: [QUESTION]; the third says what data I bring: [DATA]; exactly one ask, a 20-minute call in the next month; no adverbs, no flattery, no 'I am passionate'. Sign as [NAME], MSc [DEGREE], [UNIVERSITY]. Their recent papers: [PASTE].
A6: Colab code | B6: Any data task (Day 5) | C6: Write Python for Google Colab using pandas and matplotlib. Task: [DESCRIBE]. Data: [FILE, COLUMNS]. Rules: one cell per step with a one-line comment saying what a wrong output would look like; never modify the raw dataframe, always assign to a new name; print shapes after every merge or filter; save every figure at 300 dpi to [PATH] with the file name [YYYY-MM-DD_short-description_v1.png].
A7: Paper substitute | B7: A seed paper cannot be found (Day 2) | C7: I could not find this paper: [CITATION]. Suggest three substitutes published 2015 or later on the same question in a well-regarded field journal, giving authors, year, journal and a one-line reason each. Do not invent papers: if you are not sure a paper exists, say so and give a search string I can use on Google Scholar instead.
A8: Log reviewer | B8: Mid-month and month end | C8: Here is my research log: [PASTE]. Tell me in under 120 words: the one thing I keep postponing, the one thing I spend too long on, the single most valuable task for the next session, and one habit to stop. No encouragement.
A9: Paper note template | B9: Every note | C9: Question: Data (source, years, N): Method (one sentence): Main result (with the number): Identification worry: What it leaves open: One sentence I could cite it for: Differs from paper 1 by:
A10: Research log template | B10: Every day | C10: Time spent: What I did: What I learned: What blocked me: Tomorrow's first task:

Sheet Library
A1: Track | B1: Paper | C1: Order (1-10) | D1: Verified (x) | E1: Not found (x) | F1: Note done (x) | G1: Note
A2: A | B2: Dell, Jones and Olken (2014), What do we learn from the weather? The new climate-economy literature, Journal of Economic Literature
A3: A | B3: Dercon (2004), Growth and shocks: evidence from rural Ethiopia, Journal of Development Economics
A4: A | B4: Kazianga and Udry (2006), Consumption smoothing? Livestock, insurance and drought in rural Burkina Faso, JDE
A5: A | B5: Cole, Gine, Tobacman, Topalova, Townsend and Vickery (2013), Barriers to household risk management: evidence from India, AEJ Applied
A6: A | B6: Karlan, Osei, Osei-Akoto and Udry (2014), Agricultural decisions after relaxing credit and risk constraints, QJE
A7: A | B7: Mobarak and Rosenzweig (2013), Informal risk sharing, index insurance, and risk taking in developing countries, AER P&P
A8: A | B8: Clarke (2016), A theory of rational demand for index insurance, AEJ Micro
A9: A | B9: Jensen and Barrett (2017), Agricultural index insurance for development, Applied Economic Perspectives and Policy
A10: A | B10: Hill, Kumar, Magnan, Makhija, de Nicola, Spielman and Ward (2019), Ex ante and ex post effects of hybrid index insurance in Bangladesh, JDE
A11: A | B11: Emerick, de Janvry, Sadoulet and Dar (2016), Technological innovations, downside risk, and the modernization of agriculture, AER
A12: A | B12: Auffhammer, Hsiang, Schlenker and Sobel (2013), Using weather data and climate model output in economic analyses of climate change, Review of Environmental Economics and Policy
A13: A | B13: Burke, Hsiang and Miguel (2015), Global non-linear effect of temperature on economic production, Nature
... A31: B | B31: Hoepner, Rammal and Rezec (2011), Islamic mutual funds' financial performance and international investment style, European Journal of Finance

Sheet Venues
A1: Track | B1: Journal | C1: Open access | D1: Article length | E1: Latest issue | F1: My rank | G1: Read regularly | H1: Alert set
A2: A | B2: Journal of Development Economics
A3: A | B3: American Journal of Agricultural Economics
A4: A | B4: World Development
A5: A | B5: Food Policy
A6: A | B6: Economic Development and Cultural Change
A7: A | B7: Environment and Development Economics
A8: A | B8: AEJ: Applied Economics
A9: A | B9: Journal of Development Studies
A10: B | B10: Journal of Banking and Finance
A11: B | B11: Journal of Financial Stability
A12: B | B12: Pacific-Basin Finance Journal
A13: B | B13: Emerging Markets Review
... A17: B | B17: Journal of Islamic Accounting and Business Research

Sheet Supervisors
A1: Name | B1: Institution | C1: Country | D1: Pillar | E1: Last three papers | F1: Active grant | G1: Data I bring | H1: Constraint | I1: Rank | J1: Contact status | K1: Why me for them

Sheet Gap matrix
A1: Paper | B1: Data source | C1: Country | D1: Years | E1: Method | F1: Outcome | G1: Shock or screen | H1: Leaves open

Sheet Log
A1: Date | B1: Day | C1: Time spent (min) | D1: What I did | E1: What I learned | F1: What blocked me | G1: Tomorrow's first task
A2: 2026-09-05 | B2: 1
A3: 2026-09-06 | B3: 2
A4: 2026-09-12 | B4: 3
A5: 2026-09-13 | B5: 4
A6: 2026-09-19 | B6: 5
A7: 2026-09-20 | B7: 6
A8: 2026-09-26 | B8: 7
A9: 2026-09-27 | B9: 8

Sheet Decision
A1: Criterion | B1: Track A: Ag-climate | C1: Track B: Islamic finance
A2: Data access within a month | B2: 3 | C2: 3
A3: Fit to my background | B3: 3 | C3: 3
A4: Supervisor supply in target countries | B4: 3 | C4: 3
A5: Scholarship fit (funded, stipend, partner visa) | B5: 3 | C5: 3
A6: Publishable within 2 years | B6: 3 | C6: 3
A7: My genuine interest | B7: 3 | C7: 3
A8: Total | B8: =SUM(B2:B7) -> 18 | C8: =SUM(C2:C7) -> 18
A10: Example scores of 3 are placeholders: replace with your own 1 to 5. Within 3 points is a tie; tie-break is which dataset you can download tonight.

Sheet Tracks
A1: Track | B1: Name | C1: Question | D1: Data | E1: Supervisor hunt
A2: A | B2: Agricultural and climate risk economics | C2: Do rainfall and temperature shocks reduce farm household consumption and income in Bangladesh, and does access to credit or index insurance buffer the effect? | D2: Bangladesh Integrated Household Survey (IFPRI, Harvard Dataverse, free registration), matched to NASA POWER daily weather at the district centroid | E2: Search OpenAlex and Google Scholar for authors with 3+ papers since 2020 on 'index insurance', 'weather shocks', 'Bangladesh agriculture'. Priority institutions: Motu (NZ), Lincoln University, University of Waikato, Massey, Wageningen, IFPRI-affiliated academics, University of Reading, Sussex IDS.
A3: B | B3: Islamic finance, ESG and banking | C3: Do Shariah-compliant equity portfolios on the Dhaka Stock Exchange provide downside protection in crisis periods, and does adding ESG screening change the risk-return trade-off? | D3: DSE daily prices and the DSEX Shariah index (dsebd.org, free), Bangladesh Bank policy rates, plus a Ken French factor file for the benchmark case | E3: Search OpenAlex and Google Scholar for authors with 3+ papers since 2020 on 'Islamic equity', 'ESG screening emerging markets', 'negative interest rates banks'. Priority institutions: Durham Centre for Islamic Economics and Finance, INCEIF (Malaysia), HBKU (Qatar), KFUPM, University of Hamburg Sustainable Finance, Bangor, Reading ICMA.
